<Stats deaths="138" kills="46" player_kills="0" player_projectile_count="0" >
  <death_map>
    <E key="NULL | $damage_electricity" value="7" >
    </E>
    <E key="NULL | $damage_explosion" value="18" >
    </E>
    <E key="NULL | $damage_physicshit" value="11" >
    </E>
    <E key="NULL | damage from material: acid" value="2" >
    </E>
    <E key="NULL | damage from material: lava" value="1" >
    </E>
    <E key="drone_lasership | $damage_explosion" value="2" >
    </E>
    <E key="player | $damage_electricity" value="15" >
    </E>
    <E key="player | $damage_explosion" value="22" >
    </E>
    <E key="player | $damage_projectile" value="53" >
    </E>
    <E key="player_rng_items | $damage_projectile" value="4" >
    </E>
    <E key="scavenger_smg | $damage_projectile" value="1" >
    </E>
    <E key="sniper | $damage_projectile" value="1" >
    </E>
    <E key="tank | $damage_projectile" value="1" >
    </E>
  </death_map>
  <kill_map>
    <E key="acidshot" value="11" >
    </E>
    <E key="dripping_radioactive" value="1" >
    </E>
    <E key="drone_lasership" value="2" >
    </E>
    <E key="miner" value="3" >
    </E>
    <E key="scavenger_grenade" value="13" >
    </E>
    <E key="scavenger_mine" value="1" >
    </E>
    <E key="scavenger_smg" value="9" >
    </E>
    <E key="shotgunner" value="5" >
    </E>
    <E key="sniper" value="1" >
    </E>
  </kill_map>
</Stats>
