<Stats deaths="16" kills="4" player_kills="0" player_projectile_count="0" >
  <death_map>
    <E key="NULL | $damage_fire" value="1" >
    </E>
    <E key="NULL | $damage_physicshit" value="1" >
    </E>
    <E key="lasergun | $damage_projectile" value="1" >
    </E>
    <E key="player | $damage_electricity" value="2" >
    </E>
    <E key="player | $damage_explosion" value="6" >
    </E>
    <E key="player | $damage_projectile" value="5" >
    </E>
  </death_map>
  <kill_map>
    <E key="physics_torch_stand" value="1" >
    </E>
    <E key="scorpion" value="2" >
    </E>
    <E key="sniper" value="1" >
    </E>
  </kill_map>
</Stats>
